milton/__init__.py
milton/cfg.py
milton/err.py
milton/reader.py
milton/realtime.py
milton/utils.py
milton/writer.py
milton-190624.dist-info/LICENSE
milton-190624.dist-info/METADATA
milton-190624.dist-info/WHEEL
milton-190624.dist-info/top_level.txt
milton-190624.dist-info/RECORD
