Metadata-Version: 2.1
Name: milton
Version: 190624
Summary: Algorithmic Composition Utilities
Author-email: Amir Teymuri <amtework@gmail.com>
License: GNU GENERAL PUBLIC LICENSE
Project-URL: Homepage, https://milton.codeberg.page/
Project-URL: Bug Tracker, https://codeberg.org/milton/src/issues
Classifier: Programming Language :: Python :: 3
Classifier: License :: OSI Approved :: GNU Affero General Public License v3
Classifier: Operating System :: OS Independent
Requires-Python: >=3.5
License-File: LICENSE
Requires-Dist: python-rtmidi
Requires-Dist: MIDIUtil
Requires-Dist: mido
Requires-Dist: numpy
